Products.PluggableAuthService-3.0-py3.11-nspkg.pth
Products/PluggableAuthService/PluggableAuthService.py
Products/PluggableAuthService/PropertiedUser.py
Products/PluggableAuthService/UserPropertySheet.py
Products/PluggableAuthService/__init__.py
Products/PluggableAuthService/compatibility.zcml
Products/PluggableAuthService/configure.zcml
Products/PluggableAuthService/events.py
Products/PluggableAuthService/events.zcml
Products/PluggableAuthService/exportimport.py
Products/PluggableAuthService/exportimport.zcml
Products/PluggableAuthService/meta.zcml
Products/PluggableAuthService/permissions.py
Products/PluggableAuthService/utils.py
Products/PluggableAuthService/zcml.py
Products/PluggableAuthService/Extensions/README.txt
Products/PluggableAuthService/Extensions/__init__.py
Products/PluggableAuthService/Extensions/basic_auth.py
Products/PluggableAuthService/Extensions/upgrade.py
Products/PluggableAuthService/interfaces/__init__.py
Products/PluggableAuthService/interfaces/authservice.py
Products/PluggableAuthService/interfaces/events.py
Products/PluggableAuthService/interfaces/plugins.py
Products/PluggableAuthService/interfaces/propertysheets.py
Products/PluggableAuthService/interfaces/request.py
Products/PluggableAuthService/plugins/BasePlugin.py
Products/PluggableAuthService/plugins/ChallengeProtocolChooser.py
Products/PluggableAuthService/plugins/CookieAuthHelper.py
Products/PluggableAuthService/plugins/DelegatingMultiPlugin.py
Products/PluggableAuthService/plugins/DomainAuthHelper.py
Products/PluggableAuthService/plugins/DynamicGroupsPlugin.py
Products/PluggableAuthService/plugins/HTTPBasicAuthHelper.py
Products/PluggableAuthService/plugins/InlineAuthHelper.py
Products/PluggableAuthService/plugins/LocalRolePlugin.py
Products/PluggableAuthService/plugins/NotCompetentHelper.py
Products/PluggableAuthService/plugins/RecursiveGroupsPlugin.py
Products/PluggableAuthService/plugins/RequestTypeSniffer.py
Products/PluggableAuthService/plugins/ScriptablePlugin.py
Products.PluggableAuthService-3.0.dist-info/LICENSE.txt
Products.PluggableAuthService-3.0.dist-info/METADATA
Products.PluggableAuthService-3.0.dist-info/WHEEL
Products.PluggableAuthService-3.0.dist-info/entry_points.txt
Products.PluggableAuthService-3.0.dist-info/namespace_packages.txt
Products.PluggableAuthService-3.0.dist-info/top_level.txt
Products.PluggableAuthService-3.0.dist-info/RECORD
