Metadata-Version: 2.1
Name: Products.PluggableAuthService
Version: 3.0
Summary: Pluggable Zope authentication / authorization framework
Home-page: https://productspluggableauthservice.readthedocs.io
Author: Zope Foundation and Contributors
Author-email: zope-cmf@zope.org
License: ZPL 2.1 (http://www.zope.org/Resources/License/ZPL-2.1)
Project-URL: Documentation, https://productspluggableauthservice.readthedocs.io
Project-URL: Issue Tracker, https://github.com/zopefoundation/Products.PluggableAuthService/issues
Project-URL: Sources, https://github.com/zopefoundation/Products.PluggableAuthService
Keywords: web application server zope
Classifier: Development Status :: 5 - Production/Stable
Classifier: Framework :: Plone
Classifier: Framework :: Zope :: 5
Classifier: Intended Audience :: Developers
Classifier: License :: OSI Approved :: Zope Public License
Classifier: Programming Language :: Python
Classifier: Programming Language :: Python :: 3.7
Classifier: Programming Language :: Python :: 3.8
Classifier: Programming Language :: Python :: 3.9
Classifier: Programming Language :: Python :: 3.10
Classifier: Programming Language :: Python :: 3.11
Classifier: Topic :: Software Development
Classifier: Topic :: System :: Systems Administration :: Authentication/Directory
Requires-Python: >=3.7
License-File: LICENSE.txt
Requires-Dist: setuptools
Requires-Dist: Zope >=5
Requires-Dist: AccessControl >=4.0a1
Requires-Dist: Products.PluginRegistry >=1.6
Requires-Dist: Products.GenericSetup >=2.1.2
Requires-Dist: Products.Sessions
Requires-Dist: Products.StandardCacheManagers
Provides-Extra: docs
Requires-Dist: Sphinx ; extra == 'docs'
Requires-Dist: repoze.sphinx.autointerface ; extra == 'docs'
Provides-Extra: ip_range
Requires-Dist: IPy ; extra == 'ip_range'
